rgjc_syy/__init__.py
rgjc_syy/rgjc_syy.py
rgjc_syy-0.0.2.dist-info/LICENSE
rgjc_syy-0.0.2.dist-info/METADATA
rgjc_syy-0.0.2.dist-info/WHEEL
rgjc_syy-0.0.2.dist-info/top_level.txt
rgjc_syy-0.0.2.dist-info/RECORD
